pdtransform/__init__.py
pdtransform-0.2.dist-info/DESCRIPTION.rst
pdtransform-0.2.dist-info/METADATA
pdtransform-0.2.dist-info/RECORD
pdtransform-0.2.dist-info/WHEEL
pdtransform-0.2.dist-info/metadata.json
pdtransform-0.2.dist-info/top_level.txt
