Metadata-Version: 2.0
Name: pdtransform
Version: 0.2
Summary: Sklearn transformers that work with Pandas dataframes
Home-page: http://signal-to-noise.xyz/why-you-should-use-scikit-learns-pipeline-object.html
Author: Michele Lacchia
Author-email: michelelacchia@gmail.com
License: MIT
Keywords: sklearn pandas transformers pipeline
Platform: any
Classifier: Development Status :: 3 - Alpha
Classifier: Programming Language :: Python
Classifier: Programming Language :: Python :: 2
Classifier: Programming Language :: Python :: 2.6
Classifier: Programming Language :: Python :: 2.7
Classifier: Programming Language :: Python :: 3
Classifier: Programming Language :: Python :: 3.1
Classifier: Programming Language :: Python :: 3.2
Classifier: Programming Language :: Python :: 3.3
Classifier: Programming Language :: Python :: 3.4
Classifier: Programming Language :: Python :: 3.5
Requires-Dist: scikit-learn
Requires-Dist: pandas
